wipypedia/__init__.py
wipypedia/audio/audio.py
wipypedia/core/core.py
wipypedia/image/image.py
wipypedia/math/math.py
wipypedia/search/search.py
wipypedia/wikipedia.py
wipypedia-0.1.0.dist-info/METADATA
wipypedia-0.1.0.dist-info/WHEEL
wipypedia-0.1.0.dist-info/RECORD
