Metadata-Version: 2.1
Name: wipypedia
Version: 0.1.0
Summary: 
Author: Andrew Gigena
Author-email: mail@andrewgigena.dev
Requires-Python: >=3.10,<4.0
Classifier: Programming Language :: Python :: 3
Classifier: Programming Language :: Python :: 3.10
Classifier: Programming Language :: Python :: 3.11
Requires-Dist: librosa (>=0.10.0.post2,<0.11.0)
Requires-Dist: pillow (>=9.5.0,<10.0.0)
Requires-Dist: pydantic (>=1.10.7,<2.0.0)
Requires-Dist: pywikibot (>=8.1.2,<9.0.0)
